prauto/__init__.py
prauto/__main__.py
prauto/prepauto/__init__.py
prauto/prepauto/__main__.py
prauto/retriever/__init__.py
prauto/retriever/__main__.py
prauto/retriever/get_fasta.py
prauto/retriever/get_ligand.py
prauto/retriever/get_pdb.py
PRauto-0.214.dist-info/LICENSE
PRauto-0.214.dist-info/METADATA
PRauto-0.214.dist-info/WHEEL
PRauto-0.214.dist-info/top_level.txt
PRauto-0.214.dist-info/RECORD
